README.md
setup.py
oldfartsfinalproject/__init__.py
oldfartsfinalproject/data_preprocessing.py
oldfartsfinalproject/data_util.py
oldfartsfinalproject/feature_creation.py
oldfartsfinalproject/model_evaluation.py
oldfartsfinalproject/model_output.py
oldfartsfinalproject/test_train_split.py
oldfartsfinalproject.egg-info/PKG-INFO
oldfartsfinalproject.egg-info/SOURCES.txt
oldfartsfinalproject.egg-info/dependency_links.txt
oldfartsfinalproject.egg-info/top_level.txt
tests/__init__.py
tests/test_data_preprocessing.py
tests/test_feature_creation.py