Metadata-Version: 2.1
Name: oldfartsfinalproject
Version: 1.0.0
Summary: Computing final project
Author: Jon,ABS,Wang
License: MIT
Platform: UNKNOWN
